sqlparams/__init__.py
sqlparams/_converting.py
sqlparams/_meta.py
sqlparams/_styles.py
sqlparams/_util.py
sqlparams/typing.py
sqlparams-6.0.0.dist-info/LICENSE
sqlparams-6.0.0.dist-info/METADATA
sqlparams-6.0.0.dist-info/WHEEL
sqlparams-6.0.0.dist-info/top_level.txt
sqlparams-6.0.0.dist-info/RECORD
