Metadata-Version: 2.1
Name: sqlparams
Version: 6.0.0
Summary: Convert between various DB API 2.0 parameter styles.
Author-email: "Caleb P. Burns" <cpburnz@gmail.com>
License: MIT License
Project-URL: Source Code, https://github.com/cpburnz/python-sqlparams
Project-URL: Documentation, https://python-sql-parameters.readthedocs.io/en/latest/index.html
Project-URL: Issue Tracker, https://github.com/cpburnz/python-sqlparams/issues
Classifier: Development Status :: 5 - Production/Stable
Classifier: Intended Audience :: Developers
Classifier: License :: OSI Approved :: MIT License
Classifier: Operating System :: OS Independent
Classifier: Programming Language :: Python
Classifier: Programming Language :: Python :: 3
Classifier: Programming Language :: Python :: 3.8
Classifier: Programming Language :: Python :: 3.9
Classifier: Programming Language :: Python :: 3.10
Classifier: Programming Language :: Python :: 3.11
Classifier: Programming Language :: Python :: 3.12
Classifier: Programming Language :: Python :: Implementation :: CPython
Classifier: Programming Language :: Python :: Implementation :: PyPy
Classifier: Topic :: Database
Classifier: Topic :: Software Development :: Libraries :: Python Modules
Classifier: Topic :: Utilities
Requires-Python: >=3.8
License-File: LICENSE
